maxspin/__init__.py
maxspin/binning.py
maxspin/gamma_mh.py
maxspin/objectives.py
maxspin/pairwise.py
maxspin/spatial_information.py
maxspin-0.1.1.dist-info/METADATA
maxspin-0.1.1.dist-info/WHEEL
maxspin-0.1.1.dist-info/RECORD
