Metadata-Version: 2.1
Name: maxspin
Version: 0.1.1
Summary: Estimate spatial information in spatial -omics datasets.
Home-page: https://github.com/dcjones/maxspin
Author: Daniel C. Jones
Author-email: djones3@fredhutch.org
Requires-Python: >=3.8,<3.11
Classifier: Programming Language :: Python :: 3
Classifier: Programming Language :: Python :: 3.8
Classifier: Programming Language :: Python :: 3.9
Classifier: Programming Language :: Python :: 3.10
Requires-Dist: anndata (>=0.8.0,<0.9.0)
Requires-Dist: flax (>=0.6.9,<0.7.0)
Requires-Dist: jax (>=0.4.8,<0.5.0)
Requires-Dist: numpy (>=1.22.3,<2.0.0)
Requires-Dist: optax (>=0.1.2,<0.2.0)
Requires-Dist: scipy (>=1.8.1,<2.0.0)
Requires-Dist: squidpy (>=1.2.3,<2.0.0)
Requires-Dist: tensorflow-probability (>=0.19.0,<0.20.0)
Requires-Dist: tqdm (>=4.64.0,<5.0.0)
Project-URL: Documentation, https://github.com/dcjones/maxspin
Project-URL: Repository, https://github.com/dcjones/maxspin
